<workflowGraph name="pvivaxGeneExpressionResource">
      <param name="organismResourceXmlFile"/>
      <param name="parentDataDir"/>

  <subgraph name="Pvivax_ZB_Time_Series_ExpressionDataResource" xmlFile="loadResource.xml">
    <paramValue name="resourceName">Pvivax_ZB_Time_Series_ExpressionData</paramValue>
    <paramValue name="resourceXmlFileName">$$organismResourceXmlFile$$</paramValue>
    <paramValue name="parentDataDir">$$parentDataDir$$</paramValue>
  </subgraph>

  <subgraph name="Westenberger_vivax_ExpressionDataResource" xmlFile="loadResource.xml">
    <paramValue name="resourceName">Westenberger_vivax_ExpressionData</paramValue>
    <paramValue name="resourceXmlFileName">$$organismResourceXmlFile$$</paramValue>
    <paramValue name="parentDataDir">$$parentDataDir$$</paramValue>
  </subgraph>
</workflowGraph>
